wrapenv/__init__.py
wrapenv/wrapenv.py
wrapenv-0.1.4.dist-info/METADATA
wrapenv-0.1.4.dist-info/WHEEL
wrapenv-0.1.4.dist-info/RECORD
