Metadata-Version: 2.1
Name: wrapenv
Version: 0.1.4
Summary: A wrapper for callable functions with environments to register pre- and post-processing functions checks and modifications.
Home-page: https://github.com/AMueckl/WrapEnv
Keywords: wrapper,preprocessing,postprocessing
Author: AMueckl
Author-email: AMueckl@users.noreply.github.com
Requires-Python: >=3.7,<4.0
Classifier: Programming Language :: Python :: 3
Classifier: Programming Language :: Python :: 3.7
Classifier: Programming Language :: Python :: 3.8
Classifier: Programming Language :: Python :: 3.9
Classifier: Programming Language :: Python :: 3.10
Classifier: Programming Language :: Python :: 3.11
Project-URL: Repository, https://github.com/AMueckl/WrapEnv
